open_compute/__init__.py
open_compute/types.py
open_compute/agents/__init__.py
open_compute/agents/ai_journey_to_fhir.py
open_compute/agents/journey_to_fhir.py
open_compute/data/fhir/STU6/conceptmaps.json
open_compute/data/fhir/STU6/dataelements.json
open_compute/data/fhir/STU6/fhir.schema.json
open_compute/data/fhir/STU6/profiles-others.json
open_compute/data/fhir/STU6/profiles-resources.json
open_compute/data/fhir/STU6/profiles-types.json
open_compute/data/fhir/STU6/search-parameters.json
open_compute/data/fhir/STU6/valuesets.json
open_compute/data/fhir/STU6/version.info
open_compute/utils/__init__.py
open_compute/utils/fhir_data_loader.py
open_compute/utils/fhir_schema_loader.py
open_compute/utils/fhir_validator.py
open_compute-0.1.9.dist-info/licenses/LICENSE
open_compute-0.1.9.dist-info/METADATA
open_compute-0.1.9.dist-info/WHEEL
open_compute-0.1.9.dist-info/entry_points.txt
open_compute-0.1.9.dist-info/top_level.txt
open_compute-0.1.9.dist-info/RECORD
