Metadata-Version: 2.4
Name: open-compute
Version: 0.1.9
Summary: Open Compute - multi-agent systems for healthtech
Author-email: Jori Health <bryan@jori.health>
License: MIT
Project-URL: Homepage, https://github.com/jori-health/open-compute
Classifier: Programming Language :: Python :: 3
Classifier: Programming Language :: Python :: 3 :: Only
Classifier: License :: OSI Approved :: MIT License
Classifier: Operating System :: OS Independent
Requires-Python: >=3.9
License-File: LICENSE
Requires-Dist: requests>=2.31.0
Requires-Dist: firecrawl-py>=1.5.0
Requires-Dist: fhir.resources>=7.1.0
Requires-Dist: openai>=1.0.0
Requires-Dist: nest-asyncio>=1.5.0
Provides-Extra: dev
Requires-Dist: pytest>=7.3.0; extra == "dev"
Requires-Dist: pytest-cov>=4.0.0; extra == "dev"
Dynamic: license-file
